{
  "deck_id": "d13d2e7a-4c5c-45a1-9b2a-09738ae45ced",
  "deck_name": "vancouver pg yi",
  "event_id": 600265,
  "event_name": "Riftbound Regional Qualifier - Vancouver",
  "date": "2026-05-30",
  "place": 18,
  "username": "Paggit",
  "legend_name": "Master Yi, Wuju Bladesman",
  "sections": [
    {
      "name": "Main Deck",
      "section_type": "main",
      "cards": [
        {
          "name": "Charm",
          "quantity": 3,
          "type": "Spell"
        },
        {
          "name": "Defy",
          "quantity": 3,
          "type": "Spell"
        },
        {
          "name": "En Garde",
          "quantity": 3,
          "type": "Spell"
        },
        {
          "name": "Discipline",
          "quantity": 3,
          "type": "Spell"
        },
        {
          "name": "Lonely Poro",
          "quantity": 3,
          "type": "Unit"
        },
        {
          "name": "Punch First",
          "quantity": 3,
          "type": "Spell"
        },
        {
          "name": "Ruin Runner",
          "quantity": 3,
          "type": "Unit"
        },
        {
          "name": "Scuttle Crab",
          "quantity": 3,
          "type": "Unit"
        },
        {
          "name": "Tasty Faefolk",
          "quantity": 2,
          "type": "Unit"
        },
        {
          "name": "Zhonya's Hourglass",
          "quantity": 2,
          "type": "Gear"
        },
        {
          "name": "First Mate",
          "quantity": 2,
          "type": "Unit"
        },
        {
          "name": "Trinity Force",
          "quantity": 2,
          "type": "Gear"
        },
        {
          "name": "Desert's Call",
          "quantity": 1,
          "type": "Spell"
        },
        {
          "name": "Guardian Angel",
          "quantity": 1,
          "type": "Gear"
        },
        {
          "name": "Vilemaw",
          "quantity": 1,
          "type": "Unit"
        },
        {
          "name": "Rengar, Trophy Hunter",
          "quantity": 3,
          "type": "Unit"
        },
        {
          "name": "Poppy, Paragon",
          "quantity": 1,
          "type": "Unit"
        }
      ]
    },
    {
      "name": "Rune Pool",
      "section_type": "rune_pool",
      "cards": [
        {
          "name": "Body Rune",
          "quantity": 7,
          "type": "Rune"
        },
        {
          "name": "Calm Rune",
          "quantity": 5,
          "type": "Rune"
        }
      ]
    },
    {
      "name": "Sideboard",
      "section_type": "sideboard",
      "cards": [
        {
          "name": "Akshan, Mischievous",
          "quantity": 2,
          "type": "Unit"
        },
        {
          "name": "Back Off",
          "quantity": 2,
          "type": "Spell"
        },
        {
          "name": "Sabotage",
          "quantity": 2,
          "type": "Spell"
        },
        {
          "name": "Not So Fast",
          "quantity": 1,
          "type": "Spell"
        },
        {
          "name": "Vilemaw",
          "quantity": 1,
          "type": "Unit"
        }
      ]
    }
  ]
}