{
  "deck_id": "ec47696c-a629-40c5-b5e7-80614cd9c764",
  "deck_name": "Imported Deck 2026-04-25",
  "event_id": 502327,
  "event_name": "Riftbound Regional Qualifier: Atlanta",
  "date": "2026-04-25",
  "place": 7,
  "username": "CTCG Collin K",
  "legend_name": "Sett, The Boss",
  "sections": [
    {
      "name": "Main Deck",
      "section_type": "main",
      "cards": [
        {
          "name": "Arena Bar",
          "quantity": 3,
          "type": "Gear"
        },
        {
          "name": "First Mate",
          "quantity": 3,
          "type": "Unit"
        },
        {
          "name": "Pit Rookie",
          "quantity": 3,
          "type": "Unit"
        },
        {
          "name": "Cithria of Cloudfield",
          "quantity": 3,
          "type": "Unit"
        },
        {
          "name": "Sabotage",
          "quantity": 3,
          "type": "Spell"
        },
        {
          "name": "Call to Glory",
          "quantity": 3,
          "type": "Spell"
        },
        {
          "name": "Showstopper",
          "quantity": 3,
          "type": "Spell"
        },
        {
          "name": "Punch First",
          "quantity": 3,
          "type": "Spell"
        },
        {
          "name": "Challenge",
          "quantity": 2,
          "type": "Spell"
        },
        {
          "name": "Hidden Blade",
          "quantity": 2,
          "type": "Spell"
        },
        {
          "name": "Fae Dragon",
          "quantity": 2,
          "type": "Unit"
        },
        {
          "name": "Kinkou Monk",
          "quantity": 1,
          "type": "Unit"
        },
        {
          "name": "Sea Monkey",
          "quantity": 1,
          "type": "Unit"
        },
        {
          "name": "Fiora, Victorious",
          "quantity": 3,
          "type": "Unit"
        },
        {
          "name": "Lucian, Merciless",
          "quantity": 3,
          "type": "Unit"
        },
        {
          "name": "Akshan, Mischievous",
          "quantity": 1,
          "type": "Unit"
        }
      ]
    },
    {
      "name": "Rune Pool",
      "section_type": "rune_pool",
      "cards": [
        {
          "name": "Body Rune",
          "quantity": 7,
          "type": "Rune"
        },
        {
          "name": "Order Rune",
          "quantity": 5,
          "type": "Rune"
        }
      ]
    },
    {
      "name": "Sideboard",
      "section_type": "sideboard",
      "cards": [
        {
          "name": "Unyielding Spirit",
          "quantity": 2,
          "type": "Spell"
        },
        {
          "name": "Facebreaker",
          "quantity": 2,
          "type": "Spell"
        },
        {
          "name": "Akshan, Mischievous",
          "quantity": 2,
          "type": "Unit"
        },
        {
          "name": "Sett, Brawler",
          "quantity": 1,
          "type": "Unit"
        },
        {
          "name": "Hidden Blade",
          "quantity": 1,
          "type": "Spell"
        }
      ]
    }
  ]
}